Metadata-Version: 2.1
Name: elastic-workplace-search
Version: 0.3.0
Summary: An API client for Elastic Workplace Search
Home-page: https://github.com/elastic/workplace-search-python
Author: Elastic
Author-email: support@elastic.co
License: Apache 2.0
Keywords: elastic workplace search api
Platform: UNKNOWN
Classifier: Development Status :: 4 - Beta
Classifier: Intended Audience :: Developers
Classifier: License :: OSI Approved :: Apache Software License
Classifier: Programming Language :: Python :: 2
Classifier: Programming Language :: Python :: 2.7
Classifier: Programming Language :: Python :: 3
Classifier: Programming Language :: Python :: 3.3
Classifier: Programming Language :: Python :: 3.4
Classifier: Programming Language :: Python :: 3.5
